LICENSE
MANIFEST.in
README.md
setup.py
streamlit_token_craft.egg-info/PKG-INFO
streamlit_token_craft.egg-info/SOURCES.txt
streamlit_token_craft.egg-info/dependency_links.txt
streamlit_token_craft.egg-info/requires.txt
streamlit_token_craft.egg-info/top_level.txt
token_craft/__init__.py
token_craft/frontend/build/asset-manifest.json
token_craft/frontend/build/bootstrap.min.css
token_craft/frontend/build/index.html
token_craft/frontend/build/static/css/main.327ad280.css
token_craft/frontend/build/static/css/main.327ad280.css.map
token_craft/frontend/build/static/js/main.fbe26120.js
token_craft/frontend/build/static/js/main.fbe26120.js.LICENSE.txt
token_craft/frontend/build/static/js/main.fbe26120.js.map