Metadata-Version: 2.1
Name: streamlit-token-craft
Version: 0.2.0
Summary: streamlit custom token craft and management component
Home-page: https://github.com/stavrostheocharis/streamlit-token-craft
Author: Stavros Theocharis
Author-email: stavrostheocharis@yahoo.gr
License: UNKNOWN
Keywords: Python,Streamlit,React,JavaScript,token craft,token manager
Platform: UNKNOWN
Classifier: Programming Language :: Python :: 3
Classifier: License :: OSI Approved :: MIT License
Classifier: Operating System :: OS Independent
Requires-Python: >=3.9
License-File: LICENSE
